{
	"AbsoluteLayout": {
		"ImageView": [
			{
				"_android:id": "@+id/imageView15",
				"_android:layout_width": "300dp",
				"_android:layout_height": "300dp",
				"_android:layout_x": "0dp",
				"_android:layout_y": "0dp",
				"_app:srcCompat": "@drawable/_0"
			},
			{
				"_android:id": "@+id/imageView16",
				"_android:layout_width": "169dp",
				"_android:layout_height": "300dp",
				"_android:layout_x": "0dp",
				"_android:layout_y": "0dp",
				"_app:srcCompat": "@drawable/_1"
			},
			{
				"_android:id": "@+id/imageView17",
				"_android:layout_width": "107dp",
				"_android:layout_height": "113dp",
				"_android:layout_x": "96dp",
				"_android:layout_y": "76dp",
				"_app:srcCompat": "@drawable/_2"
			},
			{
				"_android:id": "@+id/imageView18",
				"_android:layout_width": "82dp",
				"_android:layout_height": "54dp",
				"_android:layout_x": "103dp",
				"_android:layout_y": "107dp",
				"_app:srcCompat": "@drawable/_3"
			},
			{
				"_android:id": "@+id/imageView19",
				"_android:layout_width": "97dp",
				"_android:layout_height": "70dp",
				"_android:layout_x": "103dp",
				"_android:layout_y": "111dp",
				"_app:srcCompat": "@drawable/_4"
			},
			{
				"_android:id": "@+id/imageView20",
				"_android:layout_width": "193dp",
				"_android:layout_height": "113dp",
				"_android:layout_x": "53dp",
				"_android:layout_y": "110dp",
				"_app:srcCompat": "@drawable/_5"
			},
			{
				"_android:id": "@+id/imageView21",
				"_android:layout_width": "42dp",
				"_android:layout_height": "62dp",
				"_android:layout_x": "137dp",
				"_android:layout_y": "124dp",
				"_app:srcCompat": "@drawable/_6"
			}
		],
		"TextView": [{
			"_android:id": "@+id/textView2",
			"_android:layout_width": "wrap_content",
			"_android:layout_height": "wrap_content",
			"_android:layout_x": "60dp",
			"_android:layout_y": "160dp",
			"_android:fontFamily": "@font/kids_club_house",
			"_android:letterSpacing": "0.1",
			"_android:text": "Froodie",
			"_android:textColor": "#FFFFFF",
			"_android:textSize": "33sp"
		}],
		"_xmlns:android": "http://schemas.android.com/apk/res/android",
		"_xmlns:app": "http://schemas.android.com/apk/res-auto",
		"_android:layout_width": "300dp",
		"_android:layout_height": "300dp",
		"_android:background": "@color/black"
	}
}